frasco_markdown.py
setup.py
frasco_markdown.egg-info/PKG-INFO
frasco_markdown.egg-info/SOURCES.txt
frasco_markdown.egg-info/dependency_links.txt
frasco_markdown.egg-info/not-zip-safe
frasco_markdown.egg-info/requires.txt
frasco_markdown.egg-info/top_level.txt