Metadata-Version: 1.0
Name: frasco-markdown
Version: 0.1
Summary: Markdown integration for Frasco
Home-page: http://github.com/frascoweb/frasco-markdown
Author: Maxime Bouroumeau-Fuseau
Author-email: maxime.bouroumeau@gmail.com
License: MIT
Platform: any
